leo_sat_sim/__init__.py
leo_sat_sim/cli.py
leo_sat_sim/server.py
leo_sat_sim/node_modules/satellite.js/BENCHMARK-RESULTS.md
leo_sat_sim/node_modules/satellite.js/CHANGELOG.md
leo_sat_sim/node_modules/satellite.js/LICENSE.md
leo_sat_sim/node_modules/satellite.js/ORIGINAL-PKG-INFO
leo_sat_sim/node_modules/satellite.js/README.md
leo_sat_sim/node_modules/satellite.js/eslint.config.mjs
leo_sat_sim/node_modules/satellite.js/package.json
leo_sat_sim/node_modules/satellite.js/tsconfig.json
leo_sat_sim/node_modules/satellite.js/dist/satellite.es.js
leo_sat_sim/node_modules/satellite.js/dist/satellite.js
leo_sat_sim/node_modules/satellite.js/dist/satellite.min.js
leo_sat_sim/node_modules/satellite.js/lib/common-types.js
leo_sat_sim/node_modules/satellite.js/lib/constants.js
leo_sat_sim/node_modules/satellite.js/lib/dopplerFactor.js
leo_sat_sim/node_modules/satellite.js/lib/ext.js
leo_sat_sim/node_modules/satellite.js/lib/index.js
leo_sat_sim/node_modules/satellite.js/lib/indexUmd.js
leo_sat_sim/node_modules/satellite.js/lib/io.js
leo_sat_sim/node_modules/satellite.js/lib/propagation.js
leo_sat_sim/node_modules/satellite.js/lib/sun.js
leo_sat_sim/node_modules/satellite.js/lib/transforms.js
leo_sat_sim/node_modules/satellite.js/lib/propagation/SatRec.js
leo_sat_sim/node_modules/satellite.js/lib/propagation/dpper.js
leo_sat_sim/node_modules/satellite.js/lib/propagation/dscom.js
leo_sat_sim/node_modules/satellite.js/lib/propagation/dsinit.js
leo_sat_sim/node_modules/satellite.js/lib/propagation/dspace.js
leo_sat_sim/node_modules/satellite.js/lib/propagation/gstime.js
leo_sat_sim/node_modules/satellite.js/lib/propagation/initl.js
leo_sat_sim/node_modules/satellite.js/lib/propagation/propagate.js
leo_sat_sim/node_modules/satellite.js/lib/propagation/sgp4.js
leo_sat_sim/node_modules/satellite.js/lib/propagation/sgp4init.js
leo_sat_sim/node_modules/satellite.js/types/common-types.d.ts
leo_sat_sim/node_modules/satellite.js/types/constants.d.ts
leo_sat_sim-0.1.2.dist-info/METADATA
leo_sat_sim-0.1.2.dist-info/WHEEL
leo_sat_sim-0.1.2.dist-info/entry_points.txt
leo_sat_sim-0.1.2.dist-info/top_level.txt
leo_sat_sim-0.1.2.dist-info/RECORD
