Metadata-Version: 2.4
Name: leo-sat-sim
Version: 0.1.2
Summary: A 3D satellite simulator web app.
Author: K
Requires-Python: >=3.8
Requires-Dist: flask
